onsen/__main__.py
onsen/assets/bell.wav
onsen/assets/thank_you.wav
onsen/assets/water.wav
onsen/assets/welcome.wav
onsen-0.1.1.dist-info/LICENSE
onsen-0.1.1.dist-info/METADATA
onsen-0.1.1.dist-info/WHEEL
onsen-0.1.1.dist-info/entry_points.txt
onsen-0.1.1.dist-info/top_level.txt
onsen-0.1.1.dist-info/RECORD
