Metadata-Version: 2.1
Name: onsen
Version: 0.1.1
Summary: rain sounds straight to your terminal!
Home-page: https://github.com/paulopacitti/onsen
Author: Paulo Pacitti
Author-email: ppacitti@outlook.com
License: MIT
Keywords: rain,cli,onsen,rain,focus,water,sounds,white noise
Platform: UNKNOWN
Requires-Dist: pygame
Requires-Dist: rich
